deepseqcoverageqc/__init__.py
deepseqcoverageqc/coverageQC.py
deepseqcoverageqc/panelIndexer.py
deepseqcoverageqc/panelQC.py
deepseqcoverageqc-0.3.3.dist-info/LICENSE
deepseqcoverageqc-0.3.3.dist-info/METADATA
deepseqcoverageqc-0.3.3.dist-info/WHEEL
deepseqcoverageqc-0.3.3.dist-info/entry_points.txt
deepseqcoverageqc-0.3.3.dist-info/RECORD
