Metadata-Version: 2.1
Name: deepseqcoverageqc
Version: 0.3.3
Summary: Compute coverage QC metrics for deep targeted sequencing data
Author: Pandurang Kolekar
Author-email: pandurang.kolekar@gmail.com
Requires-Python: >=3.9,<4.0
Classifier: Programming Language :: Python :: 3
Classifier: Programming Language :: Python :: 3.9
Classifier: Programming Language :: Python :: 3.10
Classifier: Programming Language :: Python :: 3.11
Requires-Dist: click (>=8.1.3,<9.0.0)
Requires-Dist: pandas (>=2.0.1,<3.0.0)
Requires-Dist: rich-click (>=1.6.1,<2.0.0)
Requires-Dist: tqdm (>=4.65.0,<5.0.0)
